{"nodes": [{"id": "docker_compose_db", "label": "Database Service (PostgreSQL)", "file_type": "code", "source_file": "docker/docker-compose.yml", "source_location": null, "source_url": null, "captured_at": null, "author": null, "contributor": null}, {"id": "docker_compose_backend", "label": "Backend Service", "file_type": "code", "source_file": "docker/docker-compose.yml", "source_location": null, "source_url": null, "captured_at": null, "author": null, "contributor": null}, {"id": "docker_compose_frontend", "label": "Frontend Service", "file_type": "code", "source_file": "docker/docker-compose.yml", "source_location": null, "source_url": null, "captured_at": null, "author": null, "contributor": null}, {"id": "docker_compose_pgdata", "label": "Postgres Data Volume", "file_type": "code", "source_file": "docker/docker-compose.yml", "source_location": null, "source_url": null, "captured_at": null, "author": null, "contributor": null}, {"id": "docker_compose_digital_twin_db", "label": "Digital Twin Database", "file_type": "concept", "source_file": "docker/docker-compose.yml", "source_location": null, "source_url": null, "captured_at": null, "author": null, "contributor": null}], "edges": [{"source": "docker_compose_backend", "target": "docker_compose_db", "relation": "references", "confidence": "EXTRACTED", "confidence_score": 1.0, "source_file": "docker/docker-compose.yml", "source_location": null, "weight": 1.0}, {"source": "docker_compose_frontend", "target": "docker_compose_backend", "relation": "references", "confidence": "EXTRACTED", "confidence_score": 1.0, "source_file": "docker/docker-compose.yml", "source_location": null, "weight": 1.0}, {"source": "docker_compose_db", "target": "docker_compose_pgdata", "relation": "shares_data_with", "confidence": "EXTRACTED", "confidence_score": 1.0, "source_file": "docker/docker-compose.yml", "source_location": null, "weight": 1.0}, {"source": "docker_compose_backend", "target": "docker_compose_db", "relation": "calls", "confidence": "INFERRED", "confidence_score": 0.9, "source_file": "docker/docker-compose.yml", "source_location": null, "weight": 1.0}, {"source": "docker_compose_db", "target": "docker_compose_digital_twin_db", "relation": "implements", "confidence": "EXTRACTED", "confidence_score": 1.0, "source_file": "docker/docker-compose.yml", "source_location": null, "weight": 1.0}], "hyperedges": []}