{
  "directed": false,
  "multigraph": false,
  "graph": {},
  "nodes": [
    {
      "label": "manage.sh",
      "file_type": "code",
      "source_file": "manage.sh",
      "source_location": "L1",
      "metadata": {
        "language": "bash",
        "kind": "file"
      },
      "community": 1,
      "norm_label": "manage.sh",
      "id": "manage_sh"
    },
    {
      "label": "manage.sh script",
      "file_type": "code",
      "source_file": "manage.sh",
      "source_location": "L1",
      "metadata": {
        "language": "bash",
        "kind": "bash_entrypoint"
      },
      "community": 1,
      "norm_label": "manage.sh script",
      "id": "home_ubuntu_code_github_raviautopilot_twin_config_manage_sh__entry"
    },
    {
      "label": "Twin Config",
      "file_type": "document",
      "source_file": "README.md",
      "source_location": null,
      "source_url": null,
      "captured_at": null,
      "author": null,
      "contributor": null,
      "community": 0,
      "norm_label": "twin config",
      "id": "readme_twin_config"
    },
    {
      "label": "db service",
      "file_type": "code",
      "source_file": "docker-compose.yml",
      "source_location": null,
      "source_url": null,
      "captured_at": null,
      "author": null,
      "contributor": null,
      "community": 0,
      "norm_label": "db service",
      "id": "docker_compose_db"
    },
    {
      "label": "digital_twin database",
      "file_type": "concept",
      "source_file": "docker-compose.yml",
      "source_location": null,
      "source_url": null,
      "captured_at": null,
      "author": null,
      "contributor": null,
      "community": 0,
      "norm_label": "digital_twin database",
      "id": "docker_compose_digital_twin"
    },
    {
      "label": "pgdata volume",
      "file_type": "code",
      "source_file": "docker-compose.yml",
      "source_location": null,
      "source_url": null,
      "captured_at": null,
      "author": null,
      "contributor": null,
      "community": 0,
      "norm_label": "pgdata volume",
      "id": "docker_compose_pgdata"
    },
    {
      "label": "volume-wipe.sh",
      "file_type": "code",
      "source_file": "volume-wipe.sh",
      "source_location": "L1",
      "metadata": {
        "language": "bash",
        "kind": "file"
      },
      "community": 2,
      "norm_label": "volume-wipe.sh",
      "id": "volume_wipe_sh"
    },
    {
      "label": "volume-wipe.sh script",
      "file_type": "code",
      "source_file": "volume-wipe.sh",
      "source_location": "L1",
      "metadata": {
        "language": "bash",
        "kind": "bash_entrypoint"
      },
      "community": 2,
      "norm_label": "volume-wipe.sh script",
      "id": "home_ubuntu_code_github_raviautopilot_twin_config_volume_wipe_sh__entry"
    },
    {
      "label": "Twin Config Dockerfile",
      "file_type": "code",
      "source_file": "docker/Dockerfile",
      "source_location": null,
      "source_url": null,
      "captured_at": null,
      "author": null,
      "contributor": null,
      "id": "dockerfile_twin_config",
      "community": 0,
      "norm_label": "twin config dockerfile"
    },
    {
      "label": "Digital Twin Database",
      "file_type": "concept",
      "source_file": "docker/docker-compose.yml",
      "source_location": null,
      "source_url": null,
      "captured_at": null,
      "author": null,
      "contributor": null,
      "id": "concept_digital_twin_db",
      "community": 0,
      "norm_label": "digital twin database"
    }
  ],
  "links": [
    {
      "relation": "contains",
      "confidence": "EXTRACTED",
      "source_file": "manage.sh",
      "source_location": "L1",
      "weight": 1.0,
      "confidence_score": 1.0,
      "source": "manage_sh",
      "target": "home_ubuntu_code_github_raviautopilot_twin_config_manage_sh__entry"
    },
    {
      "relation": "references",
      "confidence": "EXTRACTED",
      "confidence_score": 1.0,
      "source_file": "README.md",
      "source_location": null,
      "weight": 1.0,
      "source": "readme_twin_config",
      "target": "docker_compose_db"
    },
    {
      "relation": "conceptually_related_to",
      "confidence": "INFERRED",
      "confidence_score": 0.9,
      "source_file": "docker/docker-compose.yml",
      "source_location": null,
      "weight": 1.0,
      "source": "docker_compose_db",
      "target": "concept_digital_twin_db"
    },
    {
      "relation": "references",
      "confidence": "EXTRACTED",
      "confidence_score": 1.0,
      "source_file": "docker-compose.yml",
      "source_location": null,
      "weight": 1.0,
      "source": "docker_compose_db",
      "target": "docker_compose_digital_twin"
    },
    {
      "relation": "references",
      "confidence": "EXTRACTED",
      "confidence_score": 1.0,
      "source_file": "docker/docker-compose.yml",
      "source_location": null,
      "weight": 1.0,
      "source": "docker_compose_db",
      "target": "docker_compose_pgdata"
    },
    {
      "relation": "implements",
      "confidence": "EXTRACTED",
      "confidence_score": 1.0,
      "source_file": "docker/docker-compose.yml",
      "source_location": null,
      "weight": 1.0,
      "source": "docker_compose_db",
      "target": "dockerfile_twin_config"
    },
    {
      "relation": "contains",
      "confidence": "EXTRACTED",
      "source_file": "volume-wipe.sh",
      "source_location": "L1",
      "weight": 1.0,
      "confidence_score": 1.0,
      "source": "volume_wipe_sh",
      "target": "home_ubuntu_code_github_raviautopilot_twin_config_volume_wipe_sh__entry"
    }
  ],
  "hyperedges": [],
  "built_at_commit": "ee30b2292f02b13888d5d6f8366ac427941a6deb"
}